nancy/__init__.py
nancy/__main__.py
nancy/warnings_util.py
nancy-12.0.0.dist-info/licenses/COPYING
nancy-12.0.0.dist-info/METADATA
nancy-12.0.0.dist-info/WHEEL
nancy-12.0.0.dist-info/entry_points.txt
nancy-12.0.0.dist-info/top_level.txt
nancy-12.0.0.dist-info/RECORD
