Metadata-Version: 2.4
Name: nancy
Version: 12.0.0
Summary: Simple templating system
Author-email: Reuben Thomas <rrt@sc3d.org>
License-Expression: GPL-3.0-or-later
Project-URL: Homepage, https://github.com/rrthomas/nancy
Classifier: Environment :: Console
Classifier: Programming Language :: Python :: 3
Requires-Python: >=3.13
License-File: COPYING
Provides-Extra: test
Requires-Dist: pytest; extra == "test"
Requires-Dist: pytest-asyncio; extra == "test"
Dynamic: license-file
